Workbook

Sheet 📋 Instrucciones
B2: 📊 CONTROL FINANCIERO BÁSICO CON EXCEL Ejercicio práctico – El negocio de empanadas de María
B5: ¿QUÉ ES ESTE ARCHIVO? | C5: Este libro de Excel te ayuda a entender cuánto dinero genera tu negocio cada día. Fue creado siguiendo el programa de capacitación de la UISEK.
B7: ¿CÓMO ESTÁ ORGANIZADO? | C7: El archivo tiene 4 hojas (pestañas en la parte inferior de la pantalla):
B8: 📌 Hoja 1 – Instrucciones | C8: Esta hoja. Léela primero.
B9: 📌 Hoja 2 – Datos del Negocio | C9: Aquí ingresas los precios, costos y cantidad de ventas.
B10: 📌 Hoja 3 – Registro Diario | C10: Aquí ves el resumen de ingresos y gastos del día.
B11: 📌 Hoja 4 – Gastos del Hogar | C11: Aquí registras los gastos personales / del hogar de María.
B13: ¿QUÉ CELDAS PUEDO CAMBIAR? | C13: Las celdas con fondo AMARILLO son los datos que tú ingresas (números azules). Las celdas con fondo VERDE se calculan solas — ¡no podrás modificarlas!
B15: PASO 1 – Ir a 'Datos del Negocio' | C15: Revisa o cambia el precio de venta, el costo por empanada y las unidades vendidas por día. Todo lo demás se calcula automáticamente.
B16: PASO 2 – Ir a 'Registro Diario' | C16: Verás el resumen del día: ingresos totales, costos, ganancia bruta (toda la ganancia) y ganancia neta (lo que te queda después de pagar los insumos).
B17: PASO 3 – Ir a 'Gastos del Hogar' | C17: María ingresará sus gastos (mercado, servicios, transporte, etc.) para saber cuánto le queda libre después de cubrir los gastos del hogar.
B19: CONSEJO IMPORTANTE | C19: María mezcla el dinero del negocio con el del hogar. Este archivo le muestra POR QUÉ es importante separarlos: así sabe exactamente si el negocio gana o pierde.
B21: LEYENDA DE COLORES
B22: Fondo AMARILLO → dato que debes ingresar tú
B23: Fondo VERDE → resultado calculado automáticamente
B24: Texto AZUL → número que puedes modificar
B25: Texto NEGRO → fórmula (no modificar)

Sheet 📌 Datos del Negocio
B2: 🫓 DATOS DEL NEGOCIO DE MARÍA Empanadas de carne y de pollo
B4: PRODUCTO 1 – EMPANADAS DE CARNE
B5: Descripción | C5: Valor ingresado | D5: Unidad | E5: Referencia
B6: Precio de venta por empanada | C6: 1 | D6: $ | E6: Dato de María
B7: Costo por empanada de carne | C7: 0.5 | D7: $ | E7: Dato de María
B8: Unidades vendidas por día | C8: 20 | D8: unid. | E8: Estimado diario de María
B9: Ingreso bruto diario (carne) | C9: =C6*C8 -> 20 | D9: $
B10: % de ganancia (margen) | C10: =C12/C9 -> 0.5 | D10: %
B11: Costo total diario (carne) | C11: =C7*C8 -> 10 | D11: $
B12: Ganancia neta diaria (carne) | C12: =C9-C11 -> 10 | D12: $
B14: PRODUCTO 2 – EMPANADAS DE POLLO
B15: Descripción | C15: Valor ingresado | D15: Unidad | E15: Referencia
B16: Precio de venta por empanada | C16: 1 | D16: $ | E16: Dato de María
B17: Costo por empanada de pollo | C17: 0.2 | D17: $ | E17: Dato de María
B18: Unidades vendidas por día | C18: 50 | D18: unid. | E18: Estimado diario de María
B19: Ingreso bruto diario (pollo) | C19: =C16*C18 -> 50 | D19: $
B20: % de ganancia (margen) | C20: =C22/C19 -> 0.8 | D20: %
B21: Costo total diario (pollo) | C21: =C17*C18 -> 10 | D21: $
B22: Ganancia neta diaria (pollo) | C22: =C19-C21 -> 40 | D22: $

Sheet 📊 Registro Diario
B2: 📊 RESUMEN FINANCIERO DIARIO Negocio de Empanadas – María
B4: 💰 INGRESOS DEL DÍA
B5: Concepto | C5: Monto ($) | D5: Detalle
B6: Ventas – Empanadas de carne | C6: ='📌 Datos del Negocio'!C9 -> 20 | D6: unid × $
B7: Ventas – Empanadas de pollo | C7: ='📌 Datos del Negocio'!C19 -> 50 | D7: unid × $
B8: TOTAL INGRESOS DEL DÍA | C8: =SUM(C6:C7) -> 70
B10: 🧾 COSTOS DE PRODUCCIÓN DEL DÍA
B11: Concepto | C11: Monto ($) | D11: Detalle
B12: Costo de empanadas de carne | C12: ='📌 Datos del Negocio'!C11 -> 10 | D12: % del precio × unid.
B13: Costo de empanadas de pollo | C13: ='📌 Datos del Negocio'!C21 -> 10 | D13: % del precio × unid.
B14: TOTAL COSTOS DEL DÍA | C14: =SUM(C12:C13) -> 20
B16: 🏆 GANANCIA NETA DIARIA DEL NEGOCIO
B17: =C8-C14 -> 50
B19: 💡 La ganancia neta es el dinero que le queda a María DESPUÉS de pagar los ingredientes y costos de producción.
B21: ¿CUÁNTO GANA CADA PRODUCTO?
B22: Ganancia neta – Empanadas de carne | C22: ='📌 Datos del Negocio'!C12 -> 10 | D22: % × $ × unid.
B23: Ganancia neta – Empanadas de pollo | C23: ='📌 Datos del Negocio'!C22 -> 40 | D23: % × $ × unid.

Sheet 🏠 Gastos del Hogar
B2: 🏠 GASTOS DEL HOGAR – MARÍA Separar las cuentas del negocio y del hogar
B4: GASTOS PERSONALES / DEL HOGAR (puedes cambiarlos)
B5: Concepto | C5: Gasto diario ($) | D5: Notas
B6: Mercado / alimentación | C6: 5 | D6: Compras del día
B7: Transporte | C7: 2 | D7: Movilización
B8: Servicios (luz, agua…) | C8: 1.5 | D8: Prorrateo diario aprox.
B9: Otros gastos del hogar | C9: 1 | D9: Variable
B10: TOTAL GASTOS DEL HOGAR (día) | C10: =SUM(C6:C9) -> 9.5
B12: 💵 DINERO DISPONIBLE DESPUÉS DEL HOGAR
B13: ='📊 Registro Diario'!B17-C10 -> 40.5
B15: DESGLOSE DEL DÍA
B16: Ganancia neta del negocio | C16: ='📊 Registro Diario'!B17 -> 50 | D16: Viene de la hoja 'Registro Diario'
B17: ( – ) Gastos del hogar | C17: =C10 -> 9.5
B18: DINERO LIBRE AL FINAL DEL DÍA | C18: =C16-C17 -> 40.5
B20: ⚠️ IMPORTANTE: Este ejercicio muestra POR QUÉ María debe separar su dinero personal del dinero del negocio. Solo así sabe si el negocio realmente genera ganancia.
